greet123/__init__.py
greet123-0.4.dist-info/LICENSE.txt
greet123-0.4.dist-info/METADATA
greet123-0.4.dist-info/WHEEL
greet123-0.4.dist-info/top_level.txt
greet123-0.4.dist-info/RECORD
