Metadata-Version: 2.1
Name: greet123
Version: 0.4
Summary: A greeting program
Author: ANSHUMAN BARPANDA
Author-email: abarpanda04@gmail.com
Classifier: Programming Language :: Python :: 3
Classifier: License :: OSI Approved :: MIT License
Classifier: Operating System :: OS Independent
License-File: LICENSE.txt
